components/uart/uart.v



module top (
rst,
clk,
go,
txbusy,
txdata,
rxdata,
txd,
rxd,
frameerror
);

input rst;
input clk;
input go;
output reg txbusy;
input [7:0] txdata;
output reg [7:0]rxdata;
output reg txd;
input rxd;
output reg frameerror;

// internals
reg [3:0] txbitcount;
reg [1:0] txstate;
reg [1:0] txdivider;

reg [3:0] rxbitcount;
reg [1:0] rxstate;
reg [2:0] rxdivider;

reg lastrxd;

// transmit logic
always @ (posedge clk or posedge rst)
if (rst)
begin
	txd <= 1'b1;
	txbusy <= 1'b0;
	txstate <= 2'b0;
	txdivider <= 2'b0;
	frameerror <= 1'b0;
end
else
begin
	if(txstate==2'b00)							// wait for go
	begin
		if(go == 1'b1)
		begin
			txstate <= 2'b01;
			txbitcount <= 4'd8;
			txdivider <= 2'b00;
		end
	end
	
	if((txdivider == 2'b00)&&(txstate!=2'b00))
	begin
		case (txstate)
		2'b00:	begin							// isn't handled here
				end
		2'b01:	begin							// startbit
					txd <= 1'b0;
					txstate <= 2'b10;
				end
		2'b10:	begin							// 8 bit
					if(txbitcount == 3'b0)
					begin
						txstate <= 2'b11;	
					end
					else
					begin
						txd <= txdata[txbitcount-1];
						txbitcount <= txbitcount-1;
					end
				end
		2'b11:	begin							// stopbit
					txd <= 1'b1;
					txstate <= 2'b00;
				end
		endcase
		txdivider <= txdivider+1;
	end
	else
	begin
		txdivider <= txdivider+1;
	end

	txbusy <= (txstate>0);
end

// rx logic
always @ (posedge clk or posedge rst)
if (rst)
begin
	rxstate <= 2'b0;
	rxdivider <= 2'b0;
	lastrxd <= rxd;
end
else
begin
	if(rxstate==2'b00)
	begin
		if((lastrxd==1'b1)&&(rxd==1'b0))
		begin
			rxstate<=2'b01;
			rxdivider<=3'd4;
			rxbitcount<=4'd8;
			frameerror<=1'b0;
		end
	end
	else
	begin
	if((rxdivider == 3'b000)&&(rxstate!=2'b00))
	begin
		case (rxstate)
		2'b00:	begin							// isn't handled here
				end
		2'b01:	begin							// startbit
					rxstate <= 2'b10;
				end
		2'b10:	begin							// 8 bit
					if(rxbitcount == 3'b0)
					begin
						rxstate <= 2'b11;
						rxdivider <= 3'd0;
						if(rxd!=1'b1)
							frameerror<=1'b1;
					end
					else
					begin
						rxdata[rxbitcount-1]<= rxd;
						rxbitcount <= rxbitcount-1;
						rxdivider <= 3'd3;
					end
				end
		2'b11:	begin							// stopbit
					rxstate <= 2'b00;
				end
		endcase
//		rxdivider <= rxdivider-1;
	end
	else
	begin
		rxdivider <= rxdivider-1;
	end
	end
	lastrxd<=rxd;
end

endmodule

components/uart/uart_tb.v
`default_nettype none
`define DUMPSTR(x) `"x.vcd`"
`timescale 100 ns / 10 ns


module uart_tb();

// Clock signal
reg clk = 0;
always #0.5 clk = ~clk;

reg rst;
reg go;
wire txbusy;
reg [7:0] txdata;
wire [7:0] rxdata;
wire txd;
reg rxd;
wire frameerror;

top UUT (
	.rst(rst),
	.clk(clk),
	.go(go),
	.txbusy(txbusy),
	.txdata(txdata),
	.rxdata(rxdata),
	.txd(txd),
	.rxd(rxd),
	.frameerror(frameerror)
);

parameter DURATION = 50;


initial begin
  //-- File were to store the simulation results
  $dumpfile(`DUMPSTR(`VCD_OUTPUT));
  $dumpvars(0, uart_tb);

	#0	rst <= 1;
	#1	rst <= 0;
	#1	txdata <= 8'hA5;
		rxd <= 1;
		go <= 1;
	#1	go <= 0;
	
	#20	rxd <= 1'b0;	// startbit
	#4	rxd <= 1'b1;	// bit 7
	#4	rxd <= 1'b0;
	#4	rxd <= 1'b1;
	#4	rxd <= 1'b1;
	#4	rxd <= 1'b0;
	#4	rxd <= 1'b0;
	#4	rxd <= 1'b1;
	#4	rxd <= 1'b1;	// bit 0
	#4	rxd <= 1'b0;	// stop
	#4	rxd <= 1'b1;

	#10	txdata <= 8'h5A;
		go <= 1;
	#1	go <= 0;
	

   #(DURATION) $display("End of simulation");
  $finish;
end

endmodule

components/uart/uart_tb.vcd
$date
	Mon Sep 09 09:47:09 2019
$end
$version
	Icarus Verilog
$end
$timescale
	10ns
$end
$scope module uart_tb $end
$var wire 1 ! txd $end
$var wire 1 " txbusy $end
$var wire 8 # rxdata [7:0] $end
$var wire 1 $ frameerror $end
$var reg 1 % clk $end
$var reg 1 & go $end
$var reg 1 ' rst $end
$var reg 1 ( rxd $end
$var reg 8 ) txdata [7:0] $end
$scope module UUT $end
$var wire 1 % clk $end
$var wire 1 & go $end
$var wire 1 ' rst $end
$var wire 1 ( rxd $end
$var wire 8 * txdata [7:0] $end
$var reg 1 $ frameerror $end
$var reg 1 + lastrxd $end
$var reg 4 , rxbitcount [3:0] $end
$var reg 8 - rxdata [7:0] $end
$var reg 3 . rxdivider [2:0] $end
$var reg 2 / rxstate [1:0] $end
$var reg 4 0 txbitcount [3:0] $end
$var reg 1 " txbusy $end
$var reg 1 ! txd $end
$var reg 2 1 txdivider [1:0] $end
$var reg 2 2 txstate [1:0] $end
$upscope $end
$upscope $end
$enddefinitions $end
#0
$dumpvars
b0 2
b0 1
bx 0
b0 /
b0 .
bx -
bx ,
x+
bx *
bx )
x(
1'
x&
0%
0$
bx #
0"
1!
$end
#5
1%
#10
0'
0%
#15
b1 1
1%
#20
1&
1(
b10100101 )
b10100101 *
0%
#25
1+
b10 1
b1000 0
b1 2
1%
#30
0&
0%
#35
1"
b11 1
1%
#40
0%
#45
b0 1
1%
#50
0%
#55
b1 1
b10 2
0!
1%
#60
0%
#65
b10 1
1%
#70
0%
#75
b11 1
1%
#80
0%
#85
b0 1
1%
#90
0%
#95
b1 1
b111 0
1!
1%
#100
0%
#105
b10 1
1%
#110
0%
#115
b11 1
1%
#120
0%
#125
b0 1
1%
#130
0%
#135
b1 1
b110 0
0!
1%
#140
0%
#145
b10 1
1%
#150
0%
#155
b11 1
1%
#160
0%
#165
b0 1
1%
#170
0%
#175
b1 1
b101 0
1!
1%
#180
0%
#185
b10 1
1%
#190
0%
#195
b11 1
1%
#200
0%
#205
b0 1
1%
#210
0%
#215
b1 1
b100 0
0!
1%
#220
0%
#225
b10 1
1%
#230
0(
0%
#235
b11 1
0+
b1000 ,
b100 .
b1 /
1%
#240
0%
#245
b11 .
b0 1
1%
#250
0%
#255
b1 1
b11 0
b10 .
1%
#260
0%
#265
b1 .
b10 1
1%
#270
1(
0%
#275
b11 1
1+
b0 .
1%
#280
0%
#285
b10 /
b0 1
1%
#290
0%
#295
b1 1
b10 0
1!
b11 .
b111 ,
b1xxxxxxx #
b1xxxxxxx -
1%
#300
0%
#305
b10 .
b10 1
1%
#310
0(
0%
#315
b11 1
0+
b1 .
1%
#320
0%
#325
b0 .
b0 1
1%
#330
0%
#335
b1 1
b1 0
0!
b11 .
b110 ,
b10xxxxxx #
b10xxxxxx -
1%
#340
0%
#345
b10 .
b10 1
1%
#350
1(
0%
#355
b11 1
1+
b1 .
1%
#360
0%
#365
b0 .
b0 1
1%
#370
0%
#375
b1 1
b0 0
1!
b11 .
b101 ,
b101xxxxx #
b101xxxxx -
1%
#380
0%
#385
b10 .
b10 1
1%
#390
0%
#395
b11 1
b1 .
1%
#400
0%
#405
b0 .
b0 1
1%
#410
0%
#415
b1 1
b11 2
b11 .
b100 ,
b1011xxxx #
b1011xxxx -
1%
#420
0%
#425
b10 .
b10 1
1%
#430
0(
0%
#435
b11 1
0+
b1 .
1%
#440
0%
#445
b0 .
b0 1
1%
#450
0%
#455
b1 1
b0 2
b11 .
b11 ,
b10110xxx #
b10110xxx -
1%
#460
0%
#465
b10 .
0"
b10 1
1%
#470
0%
#475
b11 1
b1 .
1%
#480
0%
#485
b0 .
b0 1
1%
#490
0%
#495
b1 1
b11 .
b10 ,
b101100xx #
b101100xx -
1%
#500
0%
#505
b10 .
b10 1
1%
#510
1(
0%
#515
b11 1
1+
b1 .
1%
#520
0%
#525
b0 .
b0 1
1%
#530
0%
#535
b1 1
b11 .
b1 ,
b1011001x #
b1011001x -
1%
#540
0%
#545
b10 .
b10 1
1%
#550
0%
#555
b11 1
b1 .
1%
#560
0%
#565
b0 .
b0 1
1%
#570
0%
#575
b1 1
b11 .
b0 ,
b10110011 #
b10110011 -
1%
#580
0%
#585
b10 .
b10 1
1%
#590
0(
0%
#595
b11 1
0+
b1 .
1%
#600
0%
#605
b0 .
b0 1
1%
#610
0%
#615
b1 1
1$
b11 /
1%
#620
0%
#625
b0 /
b10 1
1%
#630
1(
0%
#635
b11 1
1+
1%
#640
0%
#645
b0 1
1%
#650
0%
#655
b1 1
1%
#660
0%
#665
b10 1
1%
#670
0%
#675
b11 1
1%
#680
0%
#685
b0 1
1%
#690
0%
#695
b1 1
1%
#700
0%
#705
b10 1
1%
#710
0%
#715
b11 1
1%
#720
0%
#725
b0 1
1%
#730
1&
b1011010 )
b1011010 *
0%
#735
b1 1
b1000 0
b1 2
1%
#740
0&
0%
#745
1"
b10 1
1%
#750
0%
#755
b11 1
1%
#760
0%
#765
b0 1
1%
#770
0%
#775
b1 1
b10 2
0!
1%
#780
0%
#785
b10 1
1%
#790
0%
#795
b11 1
1%
#800
0%
#805
b0 1
1%
#810
0%
#815
b1 1
b111 0
1%
#820
0%
#825
b10 1
1%
#830
0%
#835
b11 1
1%
#840
0%
#845
b0 1
1%
#850
0%
#855
b1 1
b110 0
1!
1%
#860
0%
#865
b10 1
1%
#870
0%
#875
b11 1
1%
#880
0%
#885
b0 1
1%
#890
0%
#895
b1 1
b101 0
0!
1%
#900
0%
#905
b10 1
1%
#910
0%
#915
b11 1
1%
#920
0%
#925
b0 1
1%
#930
0%
#935
b1 1
b100 0
1!
1%
#940
0%
#945
b10 1
1%
#950
0%
#955
b11 1
1%
#960
0%
#965
b0 1
1%
#970
0%
#975
b1 1
b11 0
1%
#980
0%
#985
b10 1
1%
#990
0%
#995
b11 1
1%
#1000
0%
#1005
b0 1
1%
#1010
0%
#1015
b1 1
b10 0
0!
1%
#1020
0%
#1025
b10 1
1%
#1030
0%
#1035
b11 1
1%
#1040
0%
#1045
b0 1
1%
#1050
0%
#1055
b1 1
b1 0
1!
1%
#1060
0%
#1065
b10 1
1%
#1070
0%
#1075
b11 1
1%
#1080
0%
#1085
b0 1
1%
#1090
0%
#1095
b1 1
b0 0
0!
1%
#1100
0%
#1105
b10 1
1%
#1110
0%
#1115
b11 1
1%
#1120
0%
#1125
b0 1
1%
#1130
0%
#1135
b1 1
b11 2
1%
#1140
0%
#1145
b10 1
1%
#1150
0%
#1155
b11 1
1%
#1160
0%
#1165
b0 1
1%
#1170
0%
#1175
b1 1
b0 2
1!
1%
#1180
0%
#1185
0"
b10 1
1%
#1190
0%
#1195
b11 1
1%
#1200
0%
#1205
b0 1
1%
#1210
0%
#1215
b1 1
1%
#1220
0%
#1225
b10 1
1%
#1230
0%
#1235
b11 1
1%
